{
  "throw_id": 31,
  "impact_frame_relative": 61,
  "data": [
    {
      "frame": 11102,
      "pos": {
        "x": 145.52,
        "y": 199.64,
        "z": 120.22
      },
      "vel": {
        "vx": 251.96,
        "vy": 648.34,
        "vz": -164.44
      },
      "is_impact": false
    },
    {
      "frame": 11103,
      "pos": {
        "x": 149.35,
        "y": 206.79,
        "z": 120.0
      },
      "vel": {
        "vx": 229.56,
        "vy": 428.6,
        "vz": -13.12
      },
      "is_impact": false
    },
    {
      "frame": 11104,
      "pos": {
        "x": 151.27,
        "y": 211.97,
        "z": 118.26
      },
      "vel": {
        "vx": 114.95,
        "vy": 310.45,
        "vz": -104.33
      },
      "is_impact": false
    },
    {
      "frame": 11105,
      "pos": {
        "x": 154.68,
        "y": 218.94,
        "z": 117.07
      },
      "vel": {
        "vx": 204.15,
        "vy": 418.01,
        "vz": -71.1
      },
      "is_impact": false
    },
    {
      "frame": 11106,
      "pos": {
        "x": 158.05,
        "y": 225.67,
        "z": 116.13
      },
      "vel": {
        "vx": 201.88,
        "vy": 403.04,
        "vz": -56.27
      },
      "is_impact": false
    },
    {
      "frame": 11107,
      "pos": {
        "x": 161.06,
        "y": 232.37,
        "z": 113.69
      },
      "vel": {
        "vx": 180.39,
        "vy": 401.62,
        "vz": -146.62
      },
      "is_impact": false
    },
    {
      "frame": 11108,
      "pos": {
        "x": 165.84,
        "y": 240.39,
        "z": 113.34
      },
      "vel": {
        "vx": 287.07,
        "vy": 481.27,
        "vz": -20.94
      },
      "is_impact": false
    },
    {
      "frame": 11109,
      "pos": {
        "x": 171.43,
        "y": 248.55,
        "z": 114.3
      },
      "vel": {
        "vx": 334.52,
        "vy": 488.84,
        "vz": 57.52
      },
      "is_impact": false
    },
    {
      "frame": 11110,
      "pos": {
        "x": 172.63,
        "y": 250.2,
        "z": 114.86
      },
      "vel": {
        "vx": 71.98,
        "vy": 98.81,
        "vz": 33.75
      },
      "is_impact": false
    },
    {
      "frame": 11137,
      "pos": {
        "x": 260.86,
        "y": 378.91,
        "z": 109.51
      },
      "vel": {
        "vx": 5288.97,
        "vy": 7715.08,
        "vz": -320.61
      },
      "is_impact": false
    },
    {
      "frame": 11140,
      "pos": {
        "x": 282.29,
        "y": 406.73,
        "z": 115.03
      },
      "vel": {
        "vx": 1283.97,
        "vy": 1667.25,
        "vz": 330.96
      },
      "is_impact": false
    },
    {
      "frame": 11178,
      "pos": {
        "x": 301.2,
        "y": 397.98,
        "z": 199.87
      },
      "vel": {
        "vx": 1133.84,
        "vy": -524.6,
        "vz": 5084.82
      },
      "is_impact": false
    },
    {
      "frame": 11179,
      "pos": {
        "x": 274.92,
        "y": 364.3,
        "z": 187.04
      },
      "vel": {
        "vx": -1575.55,
        "vy": -2018.51,
        "vz": -768.92
      },
      "is_impact": false
    },
    {
      "frame": 11180,
      "pos": {
        "x": 251.0,
        "y": 333.68,
        "z": 175.24
      },
      "vel": {
        "vx": -1433.39,
        "vy": -1835.34,
        "vz": -707.41
      },
      "is_impact": false
    },
    {
      "frame": 11181,
      "pos": {
        "x": 229.37,
        "y": 305.89,
        "z": 164.55
      },
      "vel": {
        "vx": -1296.82,
        "vy": -1665.55,
        "vz": -640.38
      },
      "is_impact": false
    },
    {
      "frame": 11182,
      "pos": {
        "x": 209.67,
        "y": 281.13,
        "z": 154.15
      },
      "vel": {
        "vx": -1180.34,
        "vy": -1484.36,
        "vz": -623.67
      },
      "is_impact": false
    },
    {
      "frame": 11183,
      "pos": {
        "x": 191.3,
        "y": 257.94,
        "z": 144.46
      },
      "vel": {
        "vx": -1101.66,
        "vy": -1390.18,
        "vz": -580.6
      },
      "is_impact": false
    },
    {
      "frame": 11184,
      "pos": {
        "x": 173.94,
        "y": 236.23,
        "z": 135.04
      },
      "vel": {
        "vx": -1040.5,
        "vy": -1301.02,
        "vz": -564.69
      },
      "is_impact": false
    },
    {
      "frame": 11185,
      "pos": {
        "x": 158.31,
        "y": 216.95,
        "z": 126.25
      },
      "vel": {
        "vx": -936.68,
        "vy": -1155.76,
        "vz": -526.79
      },
      "is_impact": false
    },
    {
      "frame": 11186,
      "pos": {
        "x": 143.7,
        "y": 198.95,
        "z": 117.97
      },
      "vel": {
        "vx": -875.63,
        "vy": -1078.73,
        "vz": -496.23
      },
      "is_impact": false
    },
    {
      "frame": 11187,
      "pos": {
        "x": 130.1,
        "y": 182.32,
        "z": 110.11
      },
      "vel": {
        "vx": -815.45,
        "vy": -996.86,
        "vz": -471.48
      },
      "is_impact": false
    },
    {
      "frame": 11188,
      "pos": {
        "x": 117.72,
        "y": 167.27,
        "z": 102.85
      },
      "vel": {
        "vx": -742.09,
        "vy": -902.3,
        "vz": -435.18
      },
      "is_impact": false
    },
    {
      "frame": 11189,
      "pos": {
        "x": 105.12,
        "y": 152.47,
        "z": 94.97
      },
      "vel": {
        "vx": -754.79,
        "vy": -886.9,
        "vz": -472.16
      },
      "is_impact": false
    },
    {
      "frame": 11190,
      "pos": {
        "x": 93.52,
        "y": 138.74,
        "z": 87.8
      },
      "vel": {
        "vx": -695.32,
        "vy": -823.14,
        "vz": -429.92
      },
      "is_impact": false
    },
    {
      "frame": 11191,
      "pos": {
        "x": 83.54,
        "y": 126.54,
        "z": 81.95
      },
      "vel": {
        "vx": -598.38,
        "vy": -731.08,
        "vz": -350.73
      },
      "is_impact": false
    },
    {
      "frame": 11193,
      "pos": {
        "x": 63.14,
        "y": 103.46,
        "z": 68.36
      },
      "vel": {
        "vx": -1222.61,
        "vy": -1383.39,
        "vz": -814.15
      },
      "is_impact": false
    },
    {
      "frame": 11194,
      "pos": {
        "x": 55.11,
        "y": 94.26,
        "z": 63.11
      },
      "vel": {
        "vx": -481.27,
        "vy": -551.33,
        "vz": -314.7
      },
      "is_impact": false
    },
    {
      "frame": 11195,
      "pos": {
        "x": 46.95,
        "y": 85.18,
        "z": 57.55
      },
      "vel": {
        "vx": -489.39,
        "vy": -544.42,
        "vz": -333.54
      },
      "is_impact": false
    },
    {
      "frame": 11196,
      "pos": {
        "x": 38.72,
        "y": 75.81,
        "z": 52.12
      },
      "vel": {
        "vx": -493.36,
        "vy": -561.94,
        "vz": -325.21
      },
      "is_impact": false
    },
    {
      "frame": 11197,
      "pos": {
        "x": 12.55,
        "y": 65.11,
        "z": 45.78
      },
      "vel": {
        "vx": -1568.82,
        "vy": -640.87,
        "vz": -380.22
      },
      "is_impact": false
    },
    {
      "frame": 11198,
      "pos": {
        "x": 11.17,
        "y": 59.35,
        "z": 40.86
      },
      "vel": {
        "vx": -82.14,
        "vy": -345.59,
        "vz": -295.06
      },
      "is_impact": false
    },
    {
      "frame": 11199,
      "pos": {
        "x": 9.33,
        "y": 52.97,
        "z": 35.19
      },
      "vel": {
        "vx": -110.31,
        "vy": -382.29,
        "vz": -339.89
      },
      "is_impact": false
    },
    {
      "frame": 11200,
      "pos": {
        "x": 7.77,
        "y": 47.85,
        "z": 29.28
      },
      "vel": {
        "vx": -93.58,
        "vy": -307.06,
        "vz": -353.81
      },
      "is_impact": false
    },
    {
      "frame": 11201,
      "pos": {
        "x": 8.27,
        "y": 42.36,
        "z": 23.34
      },
      "vel": {
        "vx": 30.06,
        "vy": -328.92,
        "vz": -355.97
      },
      "is_impact": false
    },
    {
      "frame": 11202,
      "pos": {
        "x": 8.08,
        "y": 37.12,
        "z": 17.59
      },
      "vel": {
        "vx": -11.83,
        "vy": -314.14,
        "vz": -344.85
      },
      "is_impact": false
    },
    {
      "frame": 11203,
      "pos": {
        "x": 7.76,
        "y": 31.52,
        "z": 11.2
      },
      "vel": {
        "vx": -19.03,
        "vy": -335.61,
        "vz": -383.01
      },
      "is_impact": false
    },
    {
      "frame": 11204,
      "pos": {
        "x": 8.01,
        "y": 26.83,
        "z": 5.0
      },
      "vel": {
        "vx": 15.17,
        "vy": -280.91,
        "vz": -371.94
      },
      "is_impact": false
    },
    {
      "frame": 11206,
      "pos": {
        "x": 2.18,
        "y": 15.62,
        "z": 3.88
      },
      "vel": {
        "vx": -349.93,
        "vy": -672.14,
        "vz": -67.07
      },
      "is_impact": false
    },
    {
      "frame": 11207,
      "pos": {
        "x": 2.91,
        "y": 12.99,
        "z": 9.65
      },
      "vel": {
        "vx": 44.08,
        "vy": -157.58,
        "vz": 346.06
      },
      "is_impact": false
    },
    {
      "frame": 11208,
      "pos": {
        "x": 3.48,
        "y": 10.13,
        "z": 15.44
      },
      "vel": {
        "vx": 33.95,
        "vy": -171.81,
        "vz": 346.77
      },
      "is_impact": false
    },
    {
      "frame": 11209,
      "pos": {
        "x": 3.66,
        "y": 7.41,
        "z": 19.58
      },
      "vel": {
        "vx": 10.76,
        "vy": -162.59,
        "vz": 248.35
      },
      "is_impact": false
    },
    {
      "frame": 11210,
      "pos": {
        "x": 4.37,
        "y": 4.67,
        "z": 23.94
      },
      "vel": {
        "vx": 43.02,
        "vy": -164.65,
        "vz": 261.27
      },
      "is_impact": false
    },
    {
      "frame": 11211,
      "pos": {
        "x": 4.75,
        "y": 2.01,
        "z": 27.49
      },
      "vel": {
        "vx": 22.39,
        "vy": -159.44,
        "vz": 213.21
      },
      "is_impact": false
    },
    {
      "frame": 11212,
      "pos": {
        "x": -17.59,
        "y": 8.57,
        "z": 26.08
      },
      "vel": {
        "vx": -1338.91,
        "vy": 393.41,
        "vz": -85.01
      },
      "is_impact": false
    },
    {
      "frame": 11213,
      "pos": {
        "x": -19.35,
        "y": 7.21,
        "z": 28.56
      },
      "vel": {
        "vx": -105.37,
        "vy": -81.53,
        "vz": 148.92
      },
      "is_impact": false
    },
    {
      "frame": 11214,
      "pos": {
        "x": -22.19,
        "y": 5.37,
        "z": 30.89
      },
      "vel": {
        "vx": -170.1,
        "vy": -110.05,
        "vz": 139.46
      },
      "is_impact": false
    },
    {
      "frame": 11215,
      "pos": {
        "x": -24.8,
        "y": 3.8,
        "z": 32.62
      },
      "vel": {
        "vx": -156.65,
        "vy": -94.32,
        "vz": 103.94
      },
      "is_impact": false
    },
    {
      "frame": 11216,
      "pos": {
        "x": -27.56,
        "y": 1.8,
        "z": 32.05
      },
      "vel": {
        "vx": -165.25,
        "vy": -119.81,
        "vz": -34.2
      },
      "is_impact": false
    },
    {
      "frame": 11217,
      "pos": {
        "x": -29.7,
        "y": 0.23,
        "z": 30.91
      },
      "vel": {
        "vx": -128.25,
        "vy": -94.33,
        "vz": -68.35
      },
      "is_impact": false
    },
    {
      "frame": 11218,
      "pos": {
        "x": -31.66,
        "y": -1.43,
        "z": 29.61
      },
      "vel": {
        "vx": -117.86,
        "vy": -99.39,
        "vz": -77.99
      },
      "is_impact": false
    },
    {
      "frame": 11219,
      "pos": {
        "x": -33.4,
        "y": -3.01,
        "z": 28.35
      },
      "vel": {
        "vx": -104.44,
        "vy": -94.68,
        "vz": -75.72
      },
      "is_impact": false
    },
    {
      "frame": 11220,
      "pos": {
        "x": -34.74,
        "y": -4.48,
        "z": 26.82
      },
      "vel": {
        "vx": -80.01,
        "vy": -87.87,
        "vz": -91.74
      },
      "is_impact": false
    },
    {
      "frame": 11221,
      "pos": {
        "x": -35.77,
        "y": -5.91,
        "z": 25.09
      },
      "vel": {
        "vx": -61.56,
        "vy": -86.04,
        "vz": -103.43
      },
      "is_impact": false
    },
    {
      "frame": 11222,
      "pos": {
        "x": -36.64,
        "y": -7.28,
        "z": 23.35
      },
      "vel": {
        "vx": -52.39,
        "vy": -81.77,
        "vz": -104.02
      },
      "is_impact": false
    },
    {
      "frame": 11223,
      "pos": {
        "x": 6.37,
        "y": -21.22,
        "z": 24.4
      },
      "vel": {
        "vx": 2577.82,
        "vy": -835.74,
        "vz": 62.71
      },
      "is_impact": false
    },
    {
      "frame": 11224,
      "pos": {
        "x": 6.21,
        "y": -22.84,
        "z": 21.77
      },
      "vel": {
        "vx": -9.11,
        "vy": -97.03,
        "vz": -157.68
      },
      "is_impact": false
    },
    {
      "frame": 11225,
      "pos": {
        "x": 6.44,
        "y": -24.5,
        "z": 18.48
      },
      "vel": {
        "vx": 13.31,
        "vy": -99.86,
        "vz": -197.42
      },
      "is_impact": false
    },
    {
      "frame": 11226,
      "pos": {
        "x": 6.47,
        "y": -26.08,
        "z": 15.08
      },
      "vel": {
        "vx": 1.94,
        "vy": -94.5,
        "vz": -203.37
      },
      "is_impact": false
    },
    {
      "frame": 11227,
      "pos": {
        "x": 6.51,
        "y": -27.62,
        "z": 11.45
      },
      "vel": {
        "vx": 2.6,
        "vy": -92.21,
        "vz": -217.91
      },
      "is_impact": false
    },
    {
      "frame": 11228,
      "pos": {
        "x": 6.56,
        "y": -28.98,
        "z": 7.51
      },
      "vel": {
        "vx": 2.65,
        "vy": -81.77,
        "vz": -236.33
      },
      "is_impact": false
    },
    {
      "frame": 11229,
      "pos": {
        "x": 6.44,
        "y": -30.35,
        "z": 3.26
      },
      "vel": {
        "vx": -7.04,
        "vy": -81.72,
        "vz": -254.29
      },
      "is_impact": false
    },
    {
      "frame": 11230,
      "pos": {
        "x": 6.8,
        "y": -31.92,
        "z": -1.28
      },
      "vel": {
        "vx": 21.35,
        "vy": -94.18,
        "vz": -272.38
      },
      "is_impact": true
    },
    {
      "frame": 11231,
      "pos": {
        "x": -40.8,
        "y": -16.9,
        "z": 5.19
      },
      "vel": {
        "vx": -2852.81,
        "vy": 900.36,
        "vz": 388.13
      },
      "is_impact": false
    },
    {
      "frame": 11232,
      "pos": {
        "x": -41.17,
        "y": -17.18,
        "z": 3.33
      },
      "vel": {
        "vx": -22.27,
        "vy": -16.87,
        "vz": -111.85
      },
      "is_impact": false
    },
    {
      "frame": 11236,
      "pos": {
        "x": -45.15,
        "y": -17.68,
        "z": -4.75
      },
      "vel": {
        "vx": -238.32,
        "vy": -30.08,
        "vz": -484.06
      },
      "is_impact": false
    },
    {
      "frame": 11237,
      "pos": {
        "x": -46.84,
        "y": -17.95,
        "z": -6.7
      },
      "vel": {
        "vx": -101.48,
        "vy": -15.87,
        "vz": -116.94
      },
      "is_impact": false
    },
    {
      "frame": 11250,
      "pos": {
        "x": -48.18,
        "y": -21.79,
        "z": -6.51
      },
      "vel": {
        "vx": -80.43,
        "vy": -230.49,
        "vz": 11.48
      },
      "is_impact": false
    },
    {
      "frame": 11251,
      "pos": {
        "x": -47.58,
        "y": -22.01,
        "z": -5.37
      },
      "vel": {
        "vx": 35.89,
        "vy": -13.37,
        "vz": 68.12
      },
      "is_impact": false
    },
    {
      "frame": 11252,
      "pos": {
        "x": -13.17,
        "y": -52.45,
        "z": -2.23
      },
      "vel": {
        "vx": 2062.49,
        "vy": -1824.58,
        "vz": 188.36
      },
      "is_impact": false
    },
    {
      "frame": 11254,
      "pos": {
        "x": -10.56,
        "y": -51.31,
        "z": -1.23
      },
      "vel": {
        "vx": 156.87,
        "vy": 68.49,
        "vz": 60.07
      },
      "is_impact": false
    },
    {
      "frame": 11255,
      "pos": {
        "x": -9.41,
        "y": -51.03,
        "z": -1.04
      },
      "vel": {
        "vx": 68.41,
        "vy": 16.61,
        "vz": 11.41
      },
      "is_impact": false
    }
  ]
}